input.txt
overunder.py
overunder-1.0.3.dist-info/entry_points.txt
overunder-1.0.3.dist-info/LICENSE
overunder-1.0.3.dist-info/WHEEL
overunder-1.0.3.dist-info/METADATA
overunder-1.0.3.dist-info/RECORD
