Metadata-Version: 2.1
Name: overunder
Version: 1.0.3
Summary: An interpreted programming language in Python that could receive as rules basic weaving instructions 'over' and 'under' and apply a pattern onto text.
Home-page: https://git.vvvvvvaria.org/alicestrt/overunder.git
License: GPLv3
Keywords: plaintext,weaving
Author: anxiouspeanut
Author-email: alice.strt@gmail.com
Maintainer: anxiouspeanut
Maintainer-email: alice.strt@gmail.com
Requires-Python: >=3.6,<4.0
Classifier: License :: Other/Proprietary License
Classifier: Programming Language :: Python :: 3
Classifier: Programming Language :: Python :: 3.6
Classifier: Programming Language :: Python :: 3.7
Classifier: Programming Language :: Python :: 3.8
Classifier: Programming Language :: Python :: 3.9
Project-URL: Repository, https://git.vvvvvvaria.org/alicestrt/overunder.git
